MANIFEST.in
README.rst
setup.cfg
setup.py
doc/Makefile
doc/conf.py
doc/index.rst
doc/make.bat
doc/misc.rst
doc/reference.rst
examples/adaptive-rk/adaptive-rk.py
examples/imex/imex.py
examples/implicit_euler/implicit_euler.py
examples/implicit_euler/test_implicit_euler.py
examples/rk/run_rk_method.py
examples/semi-implicit-rk/semi-implicit-rk.py
examples/stability/mr-max-eigvals.py
examples/stability/mr-stability-diagram.py
examples/stability/multirate-step-matrix.py
examples/stability/plot-stability-regions.py
examples/stability/step-matrix.py
examples/variable-coeff-wave-equation/wave-accuracy.py
examples/variable-coeff-wave-equation/wave-equation.py
leap/__init__.py
leap/implicit.py
leap/stability.py
leap/step_matrix.py
leap/transform.py
leap/version.py
leap.egg-info/PKG-INFO
leap.egg-info/SOURCES.txt
leap.egg-info/dependency_links.txt
leap.egg-info/requires.txt
leap.egg-info/top_level.txt
leap/multistep/__init__.py
leap/multistep/multirate/__init__.py
leap/rk/__init__.py
leap/rk/imex.py
test/conftest.py
test/multirate_test_systems.py
test/sim_types.f90
test/stiff_test_systems.py
test/test_ab.py
test/test_ab_squarewave.f90
test/test_codegen_fortran.py
test/test_fancy_rk.f90
test/test_imex.py
test/test_misc.py
test/test_mrab.f90
test/test_mrab_squarewave.f90
test/test_multirate.py
test/test_rk.f90
test/test_rk.py
test/test_rk_adaptive.f90
test/test_rk_adaptive_error.f90
test/test_step_matrix.py
test/timing.f90
test/utils.py